siminput/__init__.py
siminput/keyboard.pyd
siminput/keyboard.pyi
siminput-0.0.1.dist-info/licenses/LICENSE
siminput-0.0.1.dist-info/METADATA
siminput-0.0.1.dist-info/WHEEL
siminput-0.0.1.dist-info/top_level.txt
siminput-0.0.1.dist-info/RECORD
